tests/__init__.py
tests/test_lock.py
tests/test_peer.py
tests/test_pickle.py
tests/test_server_client.py
throttle_client/__init__.py
throttle_client/client.py
throttle_client/peer.py
throttle_client/status_code.py
throttle_client-0.5.9.dist-info/licenses/LICENSE
throttle_client-0.5.9.dist-info/METADATA
throttle_client-0.5.9.dist-info/WHEEL
throttle_client-0.5.9.dist-info/top_level.txt
throttle_client-0.5.9.dist-info/RECORD
