Metadata-Version: 2.4
Name: throttle_client
Version: 0.5.9
Summary: Client for Throttle. Throttle is an http semaphore service, providing semaphores for distributed systems.
Author: Markus Klein 
License: MIT License
Project-URL: Repository, https://github.com/pacman82/throttle.git
Classifier: Programming Language :: Python :: 3
Classifier: License :: OSI Approved :: MIT License
Classifier: Operating System :: OS Independent
Requires-Python: >=3.11
License-File: LICENSE
Requires-Dist: requests
Requires-Dist: tenacity
Dynamic: license-file
